num2chinese/__init__.py
num2chinese/normalizer.py
tests/__init__.py
tests/test_normalizer.py
num2chinese-0.0.2.dist-info/LICENSE
num2chinese-0.0.2.dist-info/METADATA
num2chinese-0.0.2.dist-info/WHEEL
num2chinese-0.0.2.dist-info/top_level.txt
num2chinese-0.0.2.dist-info/RECORD
