Metadata-Version: 2.1
Name: num2chinese
Version: 0.0.2
Summary: A nlp tool to transform numbers to Chinese characters
Home-page: https://github.com/linpershey/num2chinese
Author: kota
Author-email: nicolaskodak@gmail.com
License: UNKNOWN
Project-URL: Bug Tracker, https://github.com/linpershey/num2chinese/issues
Platform: UNKNOWN
Classifier: Programming Language :: Python :: 3
Classifier: License :: OSI Approved :: MIT License
Classifier: Operating System :: OS Independent
Requires-Python: >=3.6
License-File: LICENSE
